{
    "results": {
        "sunrise": "2026-02-22T11:28:43+00:00",
        "sunset": "2026-02-22T22:26:51+00:00",
        "solar_noon": "2026-02-22T16:57:47+00:00",
        "day_length": 39488,
        "civil_twilight_begin": "2026-02-22T11:01:46+00:00",
        "civil_twilight_end": "2026-02-22T22:53:49+00:00",
        "nautical_twilight_begin": "2026-02-22T10:29:08+00:00",
        "nautical_twilight_end": "2026-02-22T23:26:27+00:00",
        "astronomical_twilight_begin": "2026-02-22T09:56:38+00:00",
        "astronomical_twilight_end": "2026-02-22T23:58:56+00:00"
    },
    "status": "OK",
    "tzid": "UTC"
}